<?xml version="1.0"?>
<BillOfMaterials Version="1" Minor="2">
  <IPInstance name="fifo_16_1a8">
    <FileSets>
      <FileSet generator="apply_current_project_options_generator">
        <File name="./apply_current_project_options_generator.xlog" type="ignore" timestamp="Fri Dec 21 14:20:53 GMT 2018" checksum="0xFFFFFFFF"></File>
      </FileSet>
      <FileSet generator="model_parameter_resolution_generator">
        <File name="./model_parameter_resolution_generator.xlog" type="ignore" timestamp="Fri Dec 21 14:20:53 GMT 2018" checksum="0xFFFFFFFF"></File>
      </FileSet>
      <FileSet generator="ip_xco_generator">
        <File name="./fifo_16_1a8.xco" type="xco" timestamp="Fri Dec 21 14:18:39 GMT 2018" checksum="0x36C84DE0"></File>
      </FileSet>
      <FileSet generator="associated_files_generator">
        <File name="./fifo_16_1a8/doc/fifo_generator_v9_3_vinfo.html" type="ignore" timestamp="Sun Oct 13 18:04:38 GMT 2013" checksum="0x9B56C5A6"></File>
        <File name="./fifo_16_1a8/fifo_generator_v9_3_readme.txt" type="ignore" timestamp="Sun Oct 13 18:04:38 GMT 2013" checksum="0x4A0AA28D"></File>
      </FileSet>
      <FileSet generator="ejava_generator">
        <File name="./fifo_16_1a8/example_design/fifo_16_1a8_exdes.ucf" type="ignore" timestamp="Fri Dec 21 14:18:42 GMT 2018" checksum="0xB547BB7D"></File>
        <File name="./fifo_16_1a8/example_design/fifo_16_1a8_exdes.vhd" type="ignore" timestamp="Fri Dec 21 14:18:42 GMT 2018" checksum="0xC24872EE"></File>
        <File name="./fifo_16_1a8/implement/implement.bat" type="ignore" timestamp="Fri Dec 21 14:18:42 GMT 2018" checksum="0xBC89B036"></File>
        <File name="./fifo_16_1a8/implement/implement.sh" type="ignore" timestamp="Fri Dec 21 14:18:42 GMT 2018" checksum="0x56795FB2"></File>
        <File name="./fifo_16_1a8/implement/implement_synplify.bat" type="ignore" timestamp="Fri Dec 21 14:18:42 GMT 2018" checksum="0xDA6A8672"></File>
        <File name="./fifo_16_1a8/implement/implement_synplify.sh" type="ignore" timestamp="Fri Dec 21 14:18:42 GMT 2018" checksum="0x733792AE"></File>
        <File name="./fifo_16_1a8/implement/planAhead_ise.bat" type="ignore" timestamp="Fri Dec 21 14:18:42 GMT 2018" checksum="0xE45BC65D"></File>
        <File name="./fifo_16_1a8/implement/planAhead_ise.sh" type="ignore" timestamp="Fri Dec 21 14:18:42 GMT 2018" checksum="0xA645EFB3"></File>
        <File name="./fifo_16_1a8/implement/planAhead_ise.tcl" type="ignore" timestamp="Fri Dec 21 14:18:42 GMT 2018" checksum="0x7358D5A4"></File>
        <File name="./fifo_16_1a8/implement/xst.prj" type="ignore" timestamp="Fri Dec 21 14:18:42 GMT 2018" checksum="0x14B03CA6"></File>
        <File name="./fifo_16_1a8/implement/xst.scr" type="ignore" timestamp="Fri Dec 21 14:18:42 GMT 2018" checksum="0x68E0AB61"></File>
        <File name="./fifo_16_1a8/simulation/fifo_16_1a8_dgen.vhd" type="ignore" timestamp="Fri Dec 21 14:18:41 GMT 2018" checksum="0x213832E7"></File>
        <File name="./fifo_16_1a8/simulation/fifo_16_1a8_dverif.vhd" type="ignore" timestamp="Fri Dec 21 14:18:42 GMT 2018" checksum="0xF7E65E84"></File>
        <File name="./fifo_16_1a8/simulation/fifo_16_1a8_pctrl.vhd" type="ignore" timestamp="Fri Dec 21 14:18:42 GMT 2018" checksum="0x95DDB1FD"></File>
        <File name="./fifo_16_1a8/simulation/fifo_16_1a8_pkg.vhd" type="ignore" timestamp="Fri Dec 21 14:18:42 GMT 2018" checksum="0xF20BFB8B"></File>
        <File name="./fifo_16_1a8/simulation/fifo_16_1a8_rng.vhd" type="ignore" timestamp="Fri Dec 21 14:18:42 GMT 2018" checksum="0x5127C6EF"></File>
        <File name="./fifo_16_1a8/simulation/fifo_16_1a8_synth.vhd" type="ignore" timestamp="Fri Dec 21 14:18:42 GMT 2018" checksum="0xA8C3EDB0"></File>
        <File name="./fifo_16_1a8/simulation/fifo_16_1a8_tb.vhd" type="ignore" timestamp="Fri Dec 21 14:18:42 GMT 2018" checksum="0x6CCB5AFA"></File>
        <File name="./fifo_16_1a8/simulation/functional/simulate_isim.bat" type="ignore" timestamp="Fri Dec 21 14:18:42 GMT 2018" checksum="0x42A5682F"></File>
        <File name="./fifo_16_1a8/simulation/functional/simulate_isim.sh" type="ignore" timestamp="Fri Dec 21 14:18:42 GMT 2018" checksum="0xC1196592"></File>
        <File name="./fifo_16_1a8/simulation/functional/simulate_mti.bat" type="ignore" timestamp="Fri Dec 21 14:18:42 GMT 2018" checksum="0x0C3CDB0C"></File>
        <File name="./fifo_16_1a8/simulation/functional/simulate_mti.do" type="ignore" timestamp="Fri Dec 21 14:18:42 GMT 2018" checksum="0x2CE7A9BB"></File>
        <File name="./fifo_16_1a8/simulation/functional/simulate_mti.sh" type="ignore" timestamp="Fri Dec 21 14:18:42 GMT 2018" checksum="0x5FDBD750"></File>
        <File name="./fifo_16_1a8/simulation/functional/simulate_ncsim.sh" type="ignore" timestamp="Fri Dec 21 14:18:42 GMT 2018" checksum="0x839AF626"></File>
        <File name="./fifo_16_1a8/simulation/functional/simulate_vcs.sh" type="ignore" timestamp="Fri Dec 21 14:18:42 GMT 2018" checksum="0x2AB1171A"></File>
        <File name="./fifo_16_1a8/simulation/functional/ucli_commands.key" type="ignore" timestamp="Fri Dec 21 14:18:42 GMT 2018" checksum="0x5F5E9AD9"></File>
        <File name="./fifo_16_1a8/simulation/functional/vcs_session.tcl" type="ignore" timestamp="Fri Dec 21 14:18:42 GMT 2018" checksum="0xC28B29B1"></File>
        <File name="./fifo_16_1a8/simulation/functional/wave_isim.tcl" type="ignore" timestamp="Fri Dec 21 14:18:42 GMT 2018" checksum="0xB10299C3"></File>
        <File name="./fifo_16_1a8/simulation/functional/wave_mti.do" type="ignore" timestamp="Fri Dec 21 14:18:42 GMT 2018" checksum="0xD51B8380"></File>
        <File name="./fifo_16_1a8/simulation/functional/wave_ncsim.sv" type="ignore" timestamp="Fri Dec 21 14:18:42 GMT 2018" checksum="0x08AFC2E5"></File>
        <File name="./fifo_16_1a8/simulation/timing/simulate_isim.bat" type="ignore" timestamp="Fri Dec 21 14:18:42 GMT 2018" checksum="0xB49F9107"></File>
        <File name="./fifo_16_1a8/simulation/timing/simulate_isim.sh" type="ignore" timestamp="Fri Dec 21 14:18:42 GMT 2018" checksum="0x91F8F384"></File>
        <File name="./fifo_16_1a8/simulation/timing/simulate_mti.bat" type="ignore" timestamp="Fri Dec 21 14:18:42 GMT 2018" checksum="0x0C3CDB0C"></File>
        <File name="./fifo_16_1a8/simulation/timing/simulate_mti.do" type="ignore" timestamp="Fri Dec 21 14:18:42 GMT 2018" checksum="0x565D4465"></File>
        <File name="./fifo_16_1a8/simulation/timing/simulate_mti.sh" type="ignore" timestamp="Fri Dec 21 14:18:42 GMT 2018" checksum="0x5FDBD750"></File>
        <File name="./fifo_16_1a8/simulation/timing/simulate_ncsim.sh" type="ignore" timestamp="Fri Dec 21 14:18:42 GMT 2018" checksum="0x8367DE23"></File>
        <File name="./fifo_16_1a8/simulation/timing/simulate_vcs.sh" type="ignore" timestamp="Fri Dec 21 14:18:42 GMT 2018" checksum="0xE69B270A"></File>
        <File name="./fifo_16_1a8/simulation/timing/ucli_commands.key" type="ignore" timestamp="Fri Dec 21 14:18:42 GMT 2018" checksum="0x5F5E9AD9"></File>
        <File name="./fifo_16_1a8/simulation/timing/vcs_session.tcl" type="ignore" timestamp="Fri Dec 21 14:18:42 GMT 2018" checksum="0xEE34713C"></File>
        <File name="./fifo_16_1a8/simulation/timing/wave_isim.tcl" type="ignore" timestamp="Fri Dec 21 14:18:42 GMT 2018" checksum="0xB10299C3"></File>
        <File name="./fifo_16_1a8/simulation/timing/wave_mti.do" type="ignore" timestamp="Fri Dec 21 14:18:42 GMT 2018" checksum="0xD51B8380"></File>
        <File name="./fifo_16_1a8/simulation/timing/wave_ncsim.sv" type="ignore" timestamp="Fri Dec 21 14:18:42 GMT 2018" checksum="0x08AFC2E5"></File>
      </FileSet>
      <FileSet generator="ngc_netlist_generator">
        <File name="./fifo_16_1a8.ngc" type="ngc" timestamp="Fri Dec 21 14:20:31 GMT 2018" checksum="0xF8E6105B"></File>
      </FileSet>
      <FileSet generator="obfuscate_netlist_generator">
        <File name="./obfuscate_netlist_generator.xlog" type="ignore" timestamp="Fri Dec 21 14:20:53 GMT 2018" checksum="0xFFFFFFFF"></File>
      </FileSet>
      <FileSet generator="padded_implementation_netlist_generator">
        <File name="./padded_implementation_netlist_generator.xlog" type="ignore" timestamp="Fri Dec 21 14:20:53 GMT 2018" checksum="0xFFFFFFFF"></File>
      </FileSet>
      <FileSet generator="instantiation_template_generator">
        <File name="./fifo_16_1a8.vho" type="vho" timestamp="Fri Dec 21 14:20:32 GMT 2018" checksum="0xB86B888D"></File>
      </FileSet>
      <FileSet generator="structural_simulation_model_generator">
        <File name="./fifo_16_1a8.vhd" type="vhdl" timestamp="Fri Dec 21 14:20:32 GMT 2018" checksum="0x52E4E1A5"></File>
      </FileSet>
      <FileSet generator="all_documents_generator">
        <File name="./fifo_16_1a8/doc/fifo_generator_v9_3_readme.txt" type="ignore" timestamp="Fri Dec 21 14:20:32 GMT 2018" checksum="0x4A0AA28D"></File>
        <File name="./fifo_16_1a8/doc/fifo_generator_v9_3_vinfo.html" type="ignore" timestamp="Fri Dec 21 14:20:32 GMT 2018" checksum="0x9B56C5A6"></File>
        <File name="./fifo_16_1a8/doc/pg057-fifo-generator.pdf" type="ignore" timestamp="Fri Dec 21 14:20:32 GMT 2018" checksum="0x90F23916"></File>
      </FileSet>
      <FileSet generator="readme_documents_generator">
        <File name="./readme_documents_generator.xlog" type="ignore" timestamp="Fri Dec 21 14:20:53 GMT 2018" checksum="0xFFFFFFFF"></File>
      </FileSet>
      <FileSet generator="asy_generator">
        <File name="./fifo_16_1a8.asy" type="asy" timestamp="Fri Dec 21 14:20:35 GMT 2018" checksum="0x9D8EBA64"></File>
      </FileSet>
      <FileSet generator="xmdf_generator">
        <File name="./fifo_16_1a8_xmdf.tcl" type="tclXmdf" timestamp="Fri Dec 21 14:20:35 GMT 2018" checksum="0xD05ADCED"></File>
      </FileSet>
      <FileSet generator="synthesis_ise_generator">
        <File name="./fifo_16_1a8.gise" type="ignore" timestamp="Fri Dec 21 14:20:49 GMT 2018" checksum="0xDE52D3BD"></File>
        <File name="./fifo_16_1a8.xise" type="ignore" timestamp="Fri Dec 21 14:20:49 GMT 2018" checksum="0x60089A28"></File>
      </FileSet>
      <FileSet generator="ise_generator">
        <File name="./fifo_16_1a8.gise" type="ignore" timestamp="Fri Dec 21 14:20:53 GMT 2018" checksum="0x3E706186"></File>
        <File name="./fifo_16_1a8.xise" type="ignore" timestamp="Fri Dec 21 14:20:53 GMT 2018" checksum="0xEB28346A"></File>
      </FileSet>
      <FileSet generator="deliver_readme_generator">
        <File name="./deliver_readme_generator.xlog" type="ignore" timestamp="Fri Dec 21 14:20:53 GMT 2018" checksum="0xFFFFFFFF"></File>
      </FileSet>
      <FileSet generator="flist_generator">
        <File name="./fifo_16_1a8_flist.txt" type="ignore" timestamp="Fri Dec 21 14:20:53 GMT 2018" checksum="0x5000AA5B"></File>
      </FileSet>
    </FileSets>
  </IPInstance>
</BillOfMaterials>
